awscli_plugin_s3_proxy/__init__.py
awscli_plugin_s3_proxy-0.5.dist-info/METADATA
awscli_plugin_s3_proxy-0.5.dist-info/RECORD
awscli_plugin_s3_proxy-0.5.dist-info/WHEEL
awscli_plugin_s3_proxy-0.5.dist-info/top_level.txt
