Metadata-Version: 2.1
Name: awscli-plugin-s3-proxy
Version: 0.5
Summary: S3 proxy plugin for AWS CLI
Home-page: https://github.com/nowak-ninja/awscli-plugin-s3-proxy
Author: Sebastian Nowak
Author-email: sebastian@nowak.ninja
License: UNKNOWN
Download-URL: https://github.com/nowak-ninja/awscli-plugin-s3-proxy/archive/0.5.tar.gz
Keywords: awscli,plugin,s3,proxy
Platform: UNKNOWN
Requires-Dist: awscli (>=1.11.0)
